{"UntypedRetype": 1, "TCBReadRegisters": 2, "TCBWriteRegisters": 3, "TCBCopyRegisters": 4, "TCBConfigure": 5, "TCBSetPriority": 6, "TCBSetMCPriority": 7, "TCBSetSchedParams": 8, "TCBSetTimeoutEndpoint": 9, "TCBSetIPCBuffer": 10, "TCBSetSpace": 11, "TCBSuspend": 12, "TCBResume": 13, "TCBBindNotification": 14, "TCBUnbindNotification": 15, "TCBSetTLSBase": 16, "CNodeRevoke": 17, "CNodeDelete": 18, "CNodeCancelBadgedSends": 19, "CNodeCopy": 20, "CNodeMint": 21, "CNodeMove": 22, "CNodeMutate": 23, "CNodeRotate": 24, "IRQIssueIRQHandler": 25, "IRQAckIRQ": 26, "IRQSetIRQHandler": 27, "IRQClearIRQHandler": 28, "DomainSetSet": 29, "SchedControlConfigureFlags": 30, "SchedContextBind": 31, "SchedContextUnbind": 32, "SchedContextUnbindObject": 33, "SchedContextConsumed": 34, "SchedContextYieldTo": 35, "RISCVPageTableMap": 36, "RISCVPageTableUnmap": 37, "RISCVPageMap": 38, "RISCVPageUnmap": 39, "RISCVPageGetAddress": 40, "RISCVASIDControlMakePool": 41, "RISCVASIDPoolAssign": 42, "RISCVIRQIssueIRQHandlerTrigger": 43}